{
  "exif": {
    "SourceFile": "/mnt/sg1/uploads/stephen/iphone/recents/2021-08-24_16-07-39_1487c05b-f5ef-4871-b4dd-b809eeec25ee.jpg",
    "errors": [],
    "ExifToolVersion": 13.26,
    "FileName": "2021-08-24_16-07-39_1487c05b-f5ef-4871-b4dd-b809eeec25ee.jpg",
    "Directory": "/mnt/sg1/uploads/stephen/iphone/recents",
    "FileSize": "545 kB",
    "FileModifyDate": {
      "_ctor": "ExifDateTime",
      "year": 2021,
      "month": 8,
      "day": 24,
      "hour": 20,
      "minute": 7,
      "second": 39,
      "tzoffsetMinutes": 0,
      "rawValue": "2021:08:24 20:07:39Z",
      "zoneName": "UTC",
      "inferredZone": false
    },
    "FileAccessDate": {
      "_ctor": "ExifDateTime",
      "year": 2024,
      "month": 10,
      "day": 25,
      "hour": 9,
      "minute": 53,
      "second": 26,
      "tzoffsetMinutes": 0,
      "rawValue": "2024:10:25 09:53:26Z",
      "zoneName": "UTC",
      "inferredZone": false
    },
    "FileInodeChangeDate": {
      "_ctor": "ExifDateTime",
      "year": 2021,
      "month": 8,
      "day": 24,
      "hour": 20,
      "minute": 7,
      "second": 39,
      "tzoffsetMinutes": 0,
      "rawValue": "2021:08:24 20:07:39Z",
      "zoneName": "UTC",
      "inferredZone": false
    },
    "FilePermissions": "-rwxrwxrwx",
    "FileType": "JPEG",
    "FileTypeExtension": "jpg",
    "MIMEType": "image/jpeg",
    "JFIFVersion": 1.01,
    "ResolutionUnit": "None",
    "XResolution": 72,
    "YResolution": 72,
    "ExifByteOrder": "Big-endian (Motorola, MM)",
    "Software": "GooglePhotoScan",
    "ExifVersion": "0220",
    "DateTimeOriginal": {
      "_ctor": "ExifDateTime",
      "year": 2021,
      "month": 8,
      "day": 24,
      "hour": 15,
      "minute": 7,
      "second": 39,
      "rawValue": "2021:08:24 15:07:39",
      "inferredZone": false
    },
    "CreateDate": {
      "_ctor": "ExifDateTime",
      "year": 2021,
      "month": 8,
      "day": 24,
      "hour": 15,
      "minute": 7,
      "second": 39,
      "rawValue": "2021:08:24 15:07:39",
      "inferredZone": false
    },
    "ColorSpace": "sRGB",
    "ExifImageWidth": 3000,
    "ExifImageHeight": 2000,
    "ImageUniqueID": "7828796a99b60ce70000000000000000",
    "CurrentIPTCDigest": "5d90d6d26ef03384057e23db17e52ccc",
    "CodedCharacterSet": "UTF8",
    "ApplicationRecordVersion": 2,
    "DigitalCreationTime": {
      "_ctor": "ExifTime",
      "hour": 15,
      "minute": 7,
      "second": 39,
      "rawValue": "15:07:39+00:00",
      "zone": "UTC",
      "inferredZone": false
    },
    "DigitalCreationDate": {
      "_ctor": "ExifDate",
      "year": 2021,
      "month": 8,
      "day": 24,
      "rawValue": "2021:08:24"
    },
    "DateCreated": {
      "_ctor": "ExifDate",
      "year": 2021,
      "month": 8,
      "day": 24,
      "rawValue": "2021:08:24"
    },
    "TimeCreated": {
      "_ctor": "ExifTime",
      "hour": 15,
      "minute": 7,
      "second": 39,
      "rawValue": "15:07:39+00:00",
      "zone": "UTC",
      "inferredZone": false
    },
    "IPTCDigest": "5d90d6d26ef03384057e23db17e52ccc",
    "ImageWidth": 3000,
    "ImageHeight": 2000,
    "EncodingProcess": "Baseline DCT, Huffman coding",
    "BitsPerSample": 8,
    "ColorComponents": 3,
    "YCbCrSubSampling": "YCbCr4:2:0 (2 2)",
    "ImageSize": "3000x2000",
    "Megapixels": 6,
    "DateTimeCreated": {
      "_ctor": "ExifDateTime",
      "year": 2021,
      "month": 8,
      "day": 24,
      "hour": 15,
      "minute": 7,
      "second": 39,
      "tzoffsetMinutes": 0,
      "rawValue": "2021:08:24 15:07:39+00:00",
      "zoneName": "UTC",
      "inferredZone": false
    },
    "DigitalCreationDateTime": {
      "_ctor": "ExifDateTime",
      "year": 2021,
      "month": 8,
      "day": 24,
      "hour": 15,
      "minute": 7,
      "second": 39,
      "tzoffsetMinutes": 0,
      "rawValue": "2021:08:24 15:07:39+00:00",
      "zoneName": "UTC",
      "inferredZone": false
    },
    "warnings": []
  },
  "dominantColor": "#675c4c",
  "people": {
    "/mnt/hdd/photo-process/processed/recents/faces/2021-08-24_16-07-39_1487c05b-f5ef-4871-b4dd-b809eeec25ee__face_0.jpg": {
      "age": {
        "probability": 0.9999750852584839,
        "high": 6,
        "low": 4
      },
      "gender": {
        "probability": 1,
        "value": "female"
      },
      "pose": {
        "pitch": 15.678737635272967,
        "roll": -2.656960184161562,
        "yaw": -4.82834065376162
      },
      "box": {
        "probability": 0.9980193376541138,
        "x_max": 1537,
        "y_max": 1500,
        "x_min": 281,
        "y_min": 75
      },
      "landmarks": [
        [
          717,
          670
        ],
        [
          1134,
          679
        ],
        [
          951,
          881
        ],
        [
          731,
          1059
        ],
        [
          1115,
          1068
        ]
      ]
    }
  }
}