{
  "exif": {
    "SourceFile": "/mnt/sg1/uploads/stephen/iphone/recents/2023-03-11_17-15-33_b2f7e347-a321-4441-97ab-524ad5e91efe.jpg",
    "errors": [],
    "tz": "UTC-5",
    "tzSource": "OffsetTimeOriginal",
    "Orientation": 6,
    "ExifToolVersion": 13.26,
    "FileName": "2023-03-11_17-15-33_b2f7e347-a321-4441-97ab-524ad5e91efe.jpg",
    "Directory": "/mnt/sg1/uploads/stephen/iphone/recents",
    "FileSize": "1919 kB",
    "FileModifyDate": {
      "_ctor": "ExifDateTime",
      "year": 2023,
      "month": 3,
      "day": 11,
      "hour": 22,
      "minute": 15,
      "second": 33,
      "tzoffsetMinutes": 0,
      "rawValue": "2023:03:11 22:15:33Z",
      "zoneName": "UTC",
      "inferredZone": false
    },
    "FileAccessDate": {
      "_ctor": "ExifDateTime",
      "year": 2024,
      "month": 10,
      "day": 25,
      "hour": 9,
      "minute": 53,
      "second": 53,
      "tzoffsetMinutes": 0,
      "rawValue": "2024:10:25 09:53:53Z",
      "zoneName": "UTC",
      "inferredZone": false
    },
    "FileInodeChangeDate": {
      "_ctor": "ExifDateTime",
      "year": 2023,
      "month": 3,
      "day": 11,
      "hour": 22,
      "minute": 15,
      "second": 33,
      "tzoffsetMinutes": 0,
      "rawValue": "2023:03:11 22:15:33Z",
      "zoneName": "UTC",
      "inferredZone": false
    },
    "FilePermissions": "-rwxrwxrwx",
    "FileType": "JPEG",
    "FileTypeExtension": "jpg",
    "MIMEType": "image/jpeg",
    "ExifByteOrder": "Big-endian (Motorola, MM)",
    "Make": "Apple",
    "Model": "iPhone 11 Pro Max",
    "XResolution": 72,
    "YResolution": 72,
    "ResolutionUnit": "inches",
    "Software": "16.3.1",
    "ModifyDate": {
      "_ctor": "ExifDateTime",
      "year": 2023,
      "month": 3,
      "day": 11,
      "hour": 17,
      "minute": 15,
      "second": 33,
      "tzoffsetMinutes": -300,
      "rawValue": "2023:03:11 17:15:33",
      "zoneName": "UTC-5",
      "inferredZone": true
    },
    "HostComputer": "iPhone 11 Pro Max",
    "YCbCrPositioning": "Centered",
    "ExposureTime": "1/40",
    "FNumber": 2.2,
    "ExposureProgram": "Program AE",
    "ISO": 250,
    "ExifVersion": "0232",
    "DateTimeOriginal": {
      "_ctor": "ExifDateTime",
      "year": 2023,
      "month": 3,
      "day": 11,
      "hour": 17,
      "minute": 15,
      "second": 33,
      "tzoffsetMinutes": -300,
      "rawValue": "2023:03:11 17:15:33",
      "zoneName": "UTC-5",
      "inferredZone": true
    },
    "CreateDate": {
      "_ctor": "ExifDateTime",
      "year": 2023,
      "month": 3,
      "day": 11,
      "hour": 17,
      "minute": 15,
      "second": 33,
      "tzoffsetMinutes": -300,
      "rawValue": "2023:03:11 17:15:33",
      "zoneName": "UTC-5",
      "inferredZone": true
    },
    "OffsetTime": "-05:00",
    "OffsetTimeOriginal": "-05:00",
    "OffsetTimeDigitized": "-05:00",
    "ComponentsConfiguration": "Y, Cb, Cr, -",
    "ShutterSpeedValue": "1/40",
    "ApertureValue": 2.2,
    "BrightnessValue": 1.322470722,
    "ExposureCompensation": 0,
    "MeteringMode": "Multi-segment",
    "Flash": "On, Fired",
    "FocalLength": "2.7 mm",
    "MakerNoteVersion": 14,
    "RunTimeFlags": "Valid",
    "RunTimeValue": 794852808666,
    "RunTimeScale": 1000000000,
    "RunTimeEpoch": 0,
    "AEStable": "Yes",
    "AETarget": 200,
    "AEAverage": 127,
    "AFStable": "Yes",
    "AccelerationVector": "0.01101496349 -0.9804679157 -0.1699893624",
    "ImageCaptureType": "Portrait",
    "LivePhotoVideoIndex": 0,
    "PhotosAppFeatureFlags": 0,
    "HDRHeadroom": 0,
    "SignalToNoiseRatio": 20.85028841,
    "PhotoIdentifier": "56131BA0-5576-44B3-A9BC-8C3C490CCB7B",
    "ColorTemperature": 3568,
    "CameraType": "Back Wide Angle",
    "FocusPosition": 0,
    "SubSecTimeOriginal": "018",
    "SubSecTimeDigitized": "018",
    "FlashpixVersion": "0100",
    "ColorSpace": "Uncalibrated",
    "ExifImageWidth": 3088,
    "ExifImageHeight": 2316,
    "SensingMethod": "One-chip color area",
    "SceneType": "Directly photographed",
    "ExposureMode": "Auto",
    "WhiteBalance": "Auto",
    "FocalLengthIn35mmFormat": "30 mm",
    "SceneCaptureType": "Standard",
    "LensInfo": "2.710000038mm f/2.2",
    "LensMake": "Apple",
    "LensModel": "iPhone 11 Pro Max front camera 2.71mm f/2.2",
    "Compression": "JPEG (old-style)",
    "ThumbnailOffset": 2104,
    "ThumbnailLength": 7237,
    "XMPToolkit": "XMP Core 6.0.0",
    "CreatorTool": "16.3.1",
    "RegionInfo": {
      "AppliedToDimensions": {
        "H": 2316,
        "Unit": "pixel",
        "W": 3088
      },
      "RegionList": [
        {
          "Area": {
            "H": "0.73772020725388587",
            "Unit": "normalized",
            "W": "0.55361658031088079",
            "X": "0.38901554404145078",
            "Y": "0.49804145077720197"
          },
          "Extensions": {
            "XMP-apple-fi:AngleInfoRoll": 240,
            "XMP-apple-fi:AngleInfoYaw": 0,
            "XMP-apple-fi:ConfidenceLevel": 11,
            "XMP-apple-fi:FaceID": 2
          },
          "Type": "Face"
        }
      ]
    },
    "DateCreated": {
      "_ctor": "ExifDateTime",
      "year": 2023,
      "month": 3,
      "day": 11,
      "hour": 17,
      "minute": 15,
      "second": 33,
      "tzoffsetMinutes": -300,
      "rawValue": "2023:03:11 17:15:33",
      "zoneName": "UTC-5",
      "inferredZone": true
    },
    "ProfileCMMType": "Apple Computer Inc.",
    "ProfileVersion": "4.0.0",
    "ProfileClass": "Display Device Profile",
    "ColorSpaceData": "RGB ",
    "ProfileConnectionSpace": "XYZ ",
    "ProfileDateTime": {
      "_ctor": "ExifDateTime",
      "year": 2022,
      "month": 1,
      "day": 1,
      "hour": 0,
      "minute": 0,
      "second": 0,
      "tzoffsetMinutes": -300,
      "rawValue": "2022:01:01 00:00:00",
      "zoneName": "UTC-5",
      "inferredZone": true
    },
    "ProfileFileSignature": "acsp",
    "PrimaryPlatform": "Apple Computer Inc.",
    "CMMFlags": "Not Embedded, Independent",
    "DeviceManufacturer": "Apple Computer Inc.",
    "DeviceModel": "",
    "DeviceAttributes": "Reflective, Glossy, Positive, Color",
    "RenderingIntent": "Perceptual",
    "ConnectionSpaceIlluminant": "0.9642 1 0.82491",
    "ProfileCreator": "Apple Computer Inc.",
    "ProfileID": "ecfda38e388547c36db4bd4f7ada182f",
    "ProfileDescription": "Display P3",
    "ProfileCopyright": "Copyright Apple Inc., 2022",
    "MediaWhitePoint": "0.96419 1 0.82489",
    "RedMatrixColumn": "0.51512 0.2412 -0.00105",
    "GreenMatrixColumn": "0.29198 0.69225 0.04189",
    "BlueMatrixColumn": "0.1571 0.06657 0.78407",
    "RedTRC": {
      "_ctor": "BinaryField",
      "bytes": 32,
      "rawValue": "(Binary data 32 bytes, use -b option to extract)"
    },
    "ChromaticAdaptation": "1.04788 0.02292 -0.0502 0.02959 0.99048 -0.01706 -0.00923 0.01508 0.75168",
    "BlueTRC": {
      "_ctor": "BinaryField",
      "bytes": 32,
      "rawValue": "(Binary data 32 bytes, use -b option to extract)"
    },
    "GreenTRC": {
      "_ctor": "BinaryField",
      "bytes": 32,
      "rawValue": "(Binary data 32 bytes, use -b option to extract)"
    },
    "ImageWidth": 3088,
    "ImageHeight": 2316,
    "EncodingProcess": "Baseline DCT, Huffman coding",
    "BitsPerSample": 8,
    "ColorComponents": 3,
    "YCbCrSubSampling": "YCbCr4:2:0 (2 2)",
    "RunTimeSincePowerUp": "0:13:15",
    "Aperture": 2.2,
    "ImageSize": "3088x2316",
    "Megapixels": 7.2,
    "ScaleFactor35efl": 11.1,
    "ShutterSpeed": "1/40",
    "SubSecCreateDate": {
      "_ctor": "ExifDateTime",
      "year": 2023,
      "month": 3,
      "day": 11,
      "hour": 17,
      "minute": 15,
      "second": 33,
      "millisecond": 18,
      "tzoffsetMinutes": -300,
      "rawValue": "2023:03:11 17:15:33.018-05:00",
      "zoneName": "UTC-5",
      "inferredZone": false
    },
    "SubSecDateTimeOriginal": {
      "_ctor": "ExifDateTime",
      "year": 2023,
      "month": 3,
      "day": 11,
      "hour": 17,
      "minute": 15,
      "second": 33,
      "millisecond": 18,
      "tzoffsetMinutes": -300,
      "rawValue": "2023:03:11 17:15:33.018-05:00",
      "zoneName": "UTC-5",
      "inferredZone": false
    },
    "SubSecModifyDate": {
      "_ctor": "ExifDateTime",
      "year": 2023,
      "month": 3,
      "day": 11,
      "hour": 17,
      "minute": 15,
      "second": 33,
      "tzoffsetMinutes": -300,
      "rawValue": "2023:03:11 17:15:33-05:00",
      "zoneName": "UTC-5",
      "inferredZone": false
    },
    "ThumbnailImage": {
      "_ctor": "BinaryField",
      "bytes": 7237,
      "rawValue": "(Binary data 7237 bytes, use -b option to extract)"
    },
    "CircleOfConfusion": "0.003 mm",
    "FOV": "61.9 deg",
    "FocalLength35efl": "2.7 mm (35 mm equivalent: 30.0 mm)",
    "HyperfocalDistance": "1.23 m",
    "LightValue": 6.3,
    "LensID": "iPhone 11 Pro Max front camera 2.71mm f/2.2",
    "warnings": []
  },
  "dominantColor": "#7e6461",
  "people": {}
}